<?xml version="1.0" encoding="UTF-8"?><record_update sys_domain="global" table="sys_ux_screen">
    <sys_ux_screen action="DELETE">
        <active>true</active>
        <app_config/>
        <description/>
        <event_mappings>[ ]</event_mappings>
        <macroponent display_value="Activity">f4ffabc70a1001101939966619d34d3c</macroponent>
        <macroponent_config>{
  "table" : "@context.props.table",
  "sysId" : "@context.props.sysId",
  "label" : "",
  "bare" : true,
  "scrollable" : "none",
  "headerLevel" : "1",
  "interceptNotifications" : false,
  "propagateNotifications" : false
}</macroponent_config>
        <name>Activity Default</name>
        <order>0</order>
        <parent_macroponent display_value="Record Page(request)">b8ffabc7ad100110dc4b3868162e6a31</parent_macroponent>
        <required_translations>[]</required_translations>
        <screen_condition/>
        <screen_type display_value="Activity">f0ffabc79a10011015543651f8cc1532</screen_type>
        <sys_class_name>sys_ux_screen</sys_class_name>
        <sys_created_by>system</sys_created_by>
        <sys_created_on>2021-12-13 07:08:55</sys_created_on>
        <sys_domain>global</sys_domain>
        <sys_id>fcffabc7fd1001107013395c487eca3d</sys_id>
        <sys_mod_count>0</sys_mod_count>
        <sys_name>Activity Default</sys_name>
        <sys_overrides/>
        <sys_package display_value="Fabule" source="x_350851_fabule">61345ea5db30b010883c68d35b961921</sys_package>
        <sys_policy/>
        <sys_scope display_value="Fabule">61345ea5db30b010883c68d35b961921</sys_scope>
        <sys_update_name>sys_ux_screen_fcffabc7fd1001107013395c487eca3d</sys_update_name>
        <sys_updated_by>system</sys_updated_by>
        <sys_updated_on>2021-12-13 07:08:55</sys_updated_on>
    </sys_ux_screen>
    <sys_update_version action="INSERT_OR_UPDATE">
        <action>DELETE</action>
        <application display_value="Fabule">61345ea5db30b010883c68d35b961921</application>
        <file_path/>
        <instance_id>a638dbdfdb0e770c91232f17d496191f</instance_id>
        <instance_name>dev88383</instance_name>
        <name>sys_ux_screen_fcffabc7fd1001107013395c487eca3d</name>
        <payload><![CDATA[<?xml version="1.0" encoding="UTF-8"?><record_update sys_domain="global" table="sys_ux_screen"><sys_ux_screen action="INSERT_OR_UPDATE"><active>true</active><app_config/><description/><event_mappings>[ ]</event_mappings><macroponent display_value="Activity">f4ffabc70a1001101939966619d34d3c</macroponent><macroponent_config>{
  "table" : "@context.props.table",
  "sysId" : "@context.props.sysId",
  "label" : "",
  "bare" : true,
  "scrollable" : "none",
  "headerLevel" : "1",
  "interceptNotifications" : false,
  "propagateNotifications" : false
}</macroponent_config><name>Activity Default</name><order>0</order><parent_macroponent display_value="Record Page(request)">b8ffabc7ad100110dc4b3868162e6a31</parent_macroponent><required_translations>[]</required_translations><screen_condition/><screen_type display_value="Activity">f0ffabc79a10011015543651f8cc1532</screen_type><sys_class_name>sys_ux_screen</sys_class_name><sys_created_by>system</sys_created_by><sys_created_on>2021-12-13 07:08:55</sys_created_on><sys_domain>global</sys_domain><sys_id>fcffabc7fd1001107013395c487eca3d</sys_id><sys_mod_count>0</sys_mod_count><sys_name>Activity Default</sys_name><sys_overrides/><sys_package display_value="Fabule" source="x_350851_fabule">61345ea5db30b010883c68d35b961921</sys_package><sys_policy/><sys_scope display_value="Fabule">61345ea5db30b010883c68d35b961921</sys_scope><sys_update_name>sys_ux_screen_fcffabc7fd1001107013395c487eca3d</sys_update_name><sys_updated_by>system</sys_updated_by><sys_updated_on>2021-12-13 07:08:55</sys_updated_on></sys_ux_screen></record_update>]]></payload>
        <payload_hash>-538731631</payload_hash>
        <record_name>Activity Default</record_name>
        <reverted_from/>
        <source>29345ea5db30b010883c68d35b961923</source>
        <source_table>sys_update_set</source_table>
        <state>previous</state>
        <sys_created_by>admin</sys_created_by>
        <sys_created_on>2021-12-13 07:15:19</sys_created_on>
        <sys_id>f661ff4bdb100110883c68d35b96193b</sys_id>
        <sys_mod_count>0</sys_mod_count>
        <sys_recorded_at>17db2a555080000001</sys_recorded_at>
        <sys_updated_by>admin</sys_updated_by>
        <sys_updated_on>2021-12-13 07:15:19</sys_updated_on>
        <type>UX Screen</type>
        <update_guid>b661ff4bb2100110aa4a21642be4bd3b</update_guid>
        <update_guid_history>b661ff4bb2100110aa4a21642be4bd3b:-538731631</update_guid_history>
    </sys_update_version>
    <sys_metadata_delete action="INSERT_OR_UPDATE">
        <sys_audit_delete/>
        <sys_class_name>sys_metadata_delete</sys_class_name>
        <sys_created_by>admin</sys_created_by>
        <sys_created_on>2021-12-13 09:06:50</sys_created_on>
        <sys_db_object display_value="" name="sys_ux_screen">sys_ux_screen</sys_db_object>
        <sys_id>248597f4f14848b086ca7a5ed8d25100</sys_id>
        <sys_metadata>fcffabc7fd1001107013395c487eca3d</sys_metadata>
        <sys_mod_count>0</sys_mod_count>
        <sys_name>Activity Default</sys_name>
        <sys_package display_value="Fabule" source="x_350851_fabule">61345ea5db30b010883c68d35b961921</sys_package>
        <sys_parent/>
        <sys_policy/>
        <sys_scope display_value="Fabule">61345ea5db30b010883c68d35b961921</sys_scope>
        <sys_scope_delete display_value="">69a04a89211443308654c50e90f24100</sys_scope_delete>
        <sys_update_name>sys_ux_screen_fcffabc7fd1001107013395c487eca3d</sys_update_name>
        <sys_update_version display_value="sys_ux_screen_fcffabc7fd1001107013395c487eca3d">f661ff4bdb100110883c68d35b96193b</sys_update_version>
        <sys_updated_by>admin</sys_updated_by>
        <sys_updated_on>2021-12-13 09:06:50</sys_updated_on>
    </sys_metadata_delete>
</record_update>
